{"cameraMode":{"drawMode":0,"name":"Shaded","section":"Shading Mode"},"sceneLighting":true,"audioPlay":false,"sceneViewState":{"m_AlwaysRefresh":false,"showFog":true,"showSkybox":true,"showFlares":true,"showImageEffects":true,"showParticleSystems":true,"showVisualEffectGraphs":true,"m_FxEnabled":true},"in2DMode":false,"pivot":{"x":-37.97774124145508,"y":-69.9761962890625,"z":70.99491119384766},"rotation":{"x":0.22318482398986817,"y":-0.2678505778312683,"z":0.06398064643144608,"w":0.9352704286575317},"size":65.2140121459961,"orthographic":false}